<?xml version="1.0"?>
<!DOCTYPE hibernate-mapping PUBLIC "-//Hibernate/Hibernate Mapping DTD 3.0//EN"
"http://hibernate.sourceforge.net/hibernate-mapping-3.0.dtd">
<!-- Generated 17-Jun-2011 10:59:34 by Hibernate Tools 3.4.0.CR1 -->
<hibernate-mapping>
    <class name="webctdbexport.db.NotesItem" table="NOTES_ITEM">
        <id name="id" type="big_decimal">
            <column name="ID" precision="20" scale="0" />
            <generator class="assigned" />
        </id>
        <many-to-one name="coTemplate" class="webctdbexport.db.CoTemplate" fetch="select">
            <column name="TEMPLATE_ID" precision="20" scale="0" not-null="true" />
        </many-to-one>
        <many-to-one name="coTocLink" class="webctdbexport.db.CoTocLink" fetch="select">
            <column name="TOC_LINK_ID" precision="20" scale="0" />
        </many-to-one>
        <many-to-one name="person" class="webctdbexport.db.Person" fetch="select">
            <column name="PERSON_ID" precision="20" scale="0" not-null="true" />
        </many-to-one>
        <many-to-one name="cmsContentEntry" class="webctdbexport.db.CmsContentEntry" fetch="select">
            <column name="CONTENT_ENTRY_ID" precision="20" scale="0" />
        </many-to-one>
        <property name="notesType" type="string">
            <column name="NOTES_TYPE" length="128" not-null="true" />
        </property>
        <property name="notesHtmlEnable" type="boolean">
            <column name="NOTES_HTML_ENABLE" precision="1" scale="0" not-null="true" />
        </property>
        <property name="createTs" type="big_decimal">
            <column name="CREATE_TS" precision="20" scale="0" not-null="true" />
        </property>
        <property name="lastmodifyTs" type="big_decimal">
            <column name="LASTMODIFY_TS" precision="20" scale="0" not-null="true" />
        </property>
        <property name="title" type="string">
            <column name="TITLE" length="1000" />
        </property>
        <property name="content" type="clob">
            <column name="CONTENT" />
        </property>
    </class>
</hibernate-mapping>
